<?xml version="1.0" encoding="UTF-8"?>
<clientmap>
	<map format="atex" folder="zxostl" />
	<map format="atex" folder="zxhaug" />
	<map format="atex" folder="zxvard" />
	<map format="c360" folder="c360" />
	<map format="carweb" folder="carweb" />
	<map format="dancenter" folder="zdcenter" />
	<map format="emprof" folder="emprof" />
	<map format="itmakeriet" folder="zegaho" />
	<map format="itmakeriet" folder="zegabb" />
	<map format="itmakeriet" folder="zednbn" />
	<map format="itmakeriet" folder="zemaja" />
	<map format="itmakeriet" folder="zeadir" />
	<map format="itmakeriet" folder="zehone" />
	<map format="itmakeriet" folder="zenonor" />
	<map format="itmakeriet" folder="zenymo" />
	<map format="itmakeriet" folder="zegeg" />
	<map format="itmakeriet" folder="zekrra" />
	<map format="itmakeriet" folder="zekrha" />
	<map format="itmakeriet" folder="zeheha" />
	<map format="itmakeriet" folder="zeabbl" />
	<map format="itmakeriet" folder="zenyaa" />
	<map format="itmakeriet" folder="zerhal" />
	<map format="itmakeriet" folder="zegala" />
	<map format="itmakeriet" folder="zebbme" />
	<map format="itmakeriet" folder="zekobbl" />
	<map format="itmakeriet" folder="ftp503781" />
	<map format="itmakeriet" folder="zemors" />
	<map format="itmakeriet" folder="zekrsk" />
	<map format="itmakeriet" folder="zerhol" />
	<map format="itmakeriet" folder="zembbl" />
	<map format="itmakeriet" folder="zemoom" />
	<map format="itmakeriet" folder="zenyst" />
	<map format="itmakeriet" folder="zeheri" />
	<map format="itmakeriet" folder="zemebe" />
	<map format="itmakeriet" folder="zekrpo" />
	<map format="itmakeriet" folder="zering" />
	<map format="itmakeriet" folder="ftp1308152" />
	<map format="itmakeriet" folder="zehglnd" />
	<map format="itmakeriet" folder="ftp756825" />
	<map format="itmakeriet" folder="zekvas" />
	<map format="itmakeriet" folder="zenymt" />
	<map format="itmakeriet" folder="zeebbl" />
	<map format="itmakeriet" folder="zemorf" />
	<map format="itmakeriet" folder="zearfo" />
	<map format="itmakeriet" folder="zekrvlskog" />
	<map format="itmakeriet" folder="zerito" />
	<map format="itmakeriet" folder="zeeiev" />
	<map format="itmakeriet" folder="zedobbl" />
	<map format="itmakeriet" folder="zekraa" />
	<map format="itmakeriet" folder="zerita" />
	<map format="itmakeriet" folder="zekbbl" />
	<map format="itmakeriet" folder="zekrvfred" />
	<map format="itmakeriet" folder="zekrba" />
	<map format="itmakeriet" folder="zenyhe" />
	<map format="itmakeriet" folder="zehabo" />
	<map format="itmakeriet" folder="zearli" />
	<map format="itmakeriet" folder="zenykr" />
	<map format="itmakeriet" folder="zekrtr" />
	<map format="itmakeriet" folder="zehena" />
	<map format="itmakeriet" folder="zegaha" />
	<map format="itmakeriet" folder="zekrvls" />
	<map format="itmakeriet" folder="zelysw" />
	<map format="itmakeriet" folder="zereie" />
	<map format="itmakeriet" folder="zeitma" />
	<map format="itmakeriet" folder="zemobo" />
	<map format="itmakeriet" folder="zerbbl" />
	<map format="itmakeriet" folder="zenyle" />
	<map format="itmakeriet" folder="zerive" />
	<map format="itmakeriet" folder="zegaro" />
	<map format="itmakeriet" folder="zenosar" />
	<map format="itmakeriet" folder="zekrto" />
	<map format="itmakeriet" folder="zedrme" />
	<map format="itmakeriet" folder="zevest" />
	<map format="itmakeriet" folder="ftp1301756" />
	<map format="itmakeriet" folder="zehemo" />
	<map format="itmakeriet" folder="zenyro" />
	<map format="itmakeriet" folder="zeheko" />
	<map format="itmakeriet" folder="zehneas" />
	<map format="itmakeriet" folder="ftp21863" />
	<map format="itmakeriet" folder="ftp1228860" />
	<map format="itmakeriet" folder="zenypr" />
	<map format="itmakeriet" folder="zerham" />
	<map format="itmakeriet" folder="zekrval" />
	<map format="itmakeriet" folder="zegamo" />
	<map format="itmakeriet" folder="zekrdr" />
	<map format="itmakeriet" folder="zemebv" />
	<map format="itmakeriet" folder="zesbol" />
	<map format="itmakeriet" folder="zeeiembl" />
	<map format="itmakeriet" folder="zenotarstvg" />
	<map format="itmakeriet" folder="zerena" />
	<map format="itmakeriet" folder="ftp1228855" />
	<map format="itmakeriet" folder="zepbbl" />
	<map format="itmakeriet" folder="zenyna" />
	<map format="itmakeriet" folder="zeeie" />
	<map format="itmakeriet" folder="zeheel" />
	<map format="itmakeriet" folder="zenyne" />
	<map format="itmakeriet" folder="zekrvb" />
	<map format="itmakeriet" folder="zemoru" />
	<map format="itmakeriet" folder="zehaub" />
	<map format="itmakeriet" folder="zebrend" />
	<map format="mactive" folder="zbhall" />
	<map format="mactive" folder="zbagpo" />
	<map format="mactive" folder="zbvlan" />
	<map format="mactive" folder="zbtbbl" />
	<map format="norbooking" folder="znnorbo" />
	<map format="norgesbooking" folder="znorgesbooking" />
	<map format="onlinebooking" folder="zobooking" />
	<map format="onlinebooking" folder="zojobs" />
	<map format="onlinebooking" folder="zoravn" />
	<map format="robot" folder="zreasy" />
	<map format="robot" folder="zrrobot" />
	<map format="robot" folder="zrh4h" />
	<map format="robot" folder="zrtopt" />
	<map format="robot" folder="zrcruit" />
	<map format="robot" folder="zrutleiem" />
	<map format="robot" folder="zrfred" />
	<map format="robot" folder="zrrekr" />
	<map format="tietoenator" folder="zakvin" />
	<map format="tietoenator" folder="zahade" />
	<map format="tietoenator" folder="zaberg" />
	<map format="tietoenator" folder="zasp" />
	<map format="tietoenator" folder="zxroga" />
	<map format="tietoenator" folder="ftp609363" />
	<map format="tietoenator" folder="zateav" />
	<map format="tietoenator" folder="zbfird" />
	<map format="tietoenator" folder="zaribl" />
	<map format="tietoenator" folder="zafima" />
	<map format="tietoenator" folder="ftp485292" />
	<map format="tietoenator" folder="ftp10082" />
	<map format="tietoenator" folder="zaostp" />
	<map format="tietoenator" folder="zaglam" />
	<map format="tietoenator" folder="zahafo" />
	<map format="tietoenator" folder="zagudb" />
	<map format="tietoenator" folder="zahear" />
	<map format="tietoenator" folder="zahala" />
	<map format="tietoenator" folder="zafinn" />
	<map format="tietoenator" folder="zaospr" />
	<map format="tietoenator" folder="zaopar" />
	<map format="tietoenator" folder="zarana" />
	<map format="tietoenator" folder="zafrbl" />
	<map format="tietoenator" folder="zafrem" />
	<map format="tietoenator" folder="zatikr" />
	<map format="tietoenator" folder="zastjb" />
	<map format="tietoenator" folder="zanamd" />
	<map format="tietoenator" folder="ftp1050782" />
	<map format="tietoenator" folder="zarb" />
	<map format="tietoenator" folder="zanoly" />
	<map format="tietoenator" folder="zasoav" />
	<map format="tietoenator" folder="zanord" />
	<map format="tietoenator" folder="zahama" />
	<map format="tietoenator" folder="zaaura" />
	<map format="tietoenator" folder="zalofo" />
	<map format="tietoenator" folder="zaarbe" />
	<map format="zettxml" folder="znotar" />
	<map format="zettxml" folder="zkelly" />
	<map format="zettxml" folder="zxtest" />
	<map format="zettxml" folder="zaocrete" />
	<map format="zettxml" folder="zhrmanager" />
	<map format="zettxml" folder="zglobesoft" />
	<map format="zettxml" folder="ftp1168098" />
	<map format="zettxml" folder="ztinde" />
	<map format="zettxml" folder="ztibe" />
	<map format="zettxml" folder="ftp595557" />
	<map format="zettxml" folder="triolink" />
	<map format="zettxml" folder="zkond" />
</clientmap>
